sharpenCommander/__init__.py
sharpenCommander/ansiTerm.py
sharpenCommander/dlgAck.py
sharpenCommander/dlgFind.py
sharpenCommander/globalBase.py
sharpenCommander/mainGit.py
sharpenCommander/mainGitStatus.py
sharpenCommander/mainGoto.py
sharpenCommander/mainRegList.py
sharpenCommander/myutil.py
sharpenCommander/run.py
sharpenCommander/sc.py
sharpenCommander/script-bash.sh
sharpenCommander/script-fish.sh
sharpenCommander/tool.py
sharpenCommander/urwidHelper.py
sharpenCommander/virenv-bash.sh
sharpenCommander/virenv-fish.sh
sharpen_commander-0.4.0.dist-info/LICENSE
sharpen_commander-0.4.0.dist-info/METADATA
sharpen_commander-0.4.0.dist-info/WHEEL
sharpen_commander-0.4.0.dist-info/entry_points.txt
sharpen_commander-0.4.0.dist-info/top_level.txt
sharpen_commander-0.4.0.dist-info/RECORD
