Metadata-Version: 2.1
Name: sharpen-commander
Version: 0.4.0
Summary: Console based Moving to folders. GIT repo management tool.
Home-page: https://github.com/cjng96/sharpenCommander
Author: Felix Choi
Author-email: cjng96@gmail.com
License: LGPL
Keywords: git management,folder management
Platform: Posix; MacOS X; Windows
Classifier: Operating System :: OS Independent
Classifier: Programming Language :: Python
Classifier: Programming Language :: Python :: 3
Classifier: Programming Language :: Python :: 3.2
Classifier: Programming Language :: Python :: 3.3
Classifier: Programming Language :: Python :: 3.4
Classifier: Programming Language :: Python :: 3.5
Classifier: Programming Language :: Python :: 3.6
Classifier: Programming Language :: Python :: 3.7
Classifier: Programming Language :: Python :: 3.8
Requires-Python: >=3
Requires-Dist: click
Requires-Dist: urwid
Requires-Dist: PyYAML
